MANIFEST.in
setup.py
dedupe/variables/__init__.py
dedupe/variables/employer.py
dedupe_variable_employer.egg-info/PKG-INFO
dedupe_variable_employer.egg-info/SOURCES.txt
dedupe_variable_employer.egg-info/dependency_links.txt
dedupe_variable_employer.egg-info/requires.txt
dedupe_variable_employer.egg-info/top_level.txt