Metadata-Version: 1.0
Name: dedupe-variable-employer
Version: 0.0.3
Summary: Employer variable type for dedupe
Home-page: https://github.com/datamade/dedupe-variables-employer
Author: UNKNOWN
Author-email: UNKNOWN
License: The MIT License: http://www.opensource.org/licenses/mit-license.php
Platform: UNKNOWN
